{"U+rqsckcjv40HfmFAPmEDA==":"mbr-1920x1277.jpg","UAj8EvgVpM7VIXdwrZEY7g==":"mbr-1920x1282.jpg","mgmytweHIlCecwUqs/aapw==":"mbr-96x87.png","JT9fylf3FYA7BJwy+UTpig==":"mbr-1920x1280.jpg","KmRTIXa0ahhrFAWalTWHwg==":"mbr-1900x1267.jpg","1Cwq7E046MDmK4LjLZaeWA==":"mbr-1900x1267.jpeg","+RHFmGaSu9iGmIX/JfkbjA==":"mbr-1673x1115.jpg","kvA2hWQ/zlwU0OG7PIV+Pg==":"mbr-1673x1129.jpg","OLmYO+bePvcusX13KeGKwg==":"mbr-1-1900x1267.jpg","1e+USPLo2oZLK2Z9zAuPOQ==":"mbr-1920x1281.jpg","fazy1peSA9NieGaopNJ2fA==":"mbr-1920x1440.jpg","aWMQKvM8tOMiuAa4cCu9iA==":"mbr-1-1920x1280.jpg"}